dankbot/__init__.py
dankbot/_version.py
dankbot/cli.py
dankbot/dankbot.py
dankbot/db.py
dankbot/memes.py
dankbot-0.0.6.dist-info/DESCRIPTION.rst
dankbot-0.0.6.dist-info/METADATA
dankbot-0.0.6.dist-info/RECORD
dankbot-0.0.6.dist-info/WHEEL
dankbot-0.0.6.dist-info/entry_points.txt
dankbot-0.0.6.dist-info/metadata.json
dankbot-0.0.6.dist-info/top_level.txt
tests/__init__.py
tests/conftest.py
tests/test_cli.py
tests/test_dankbot.py
tests/test_memes.py
