Metadata-Version: 2.0
Name: dankbot
Version: 0.0.6
Summary: Slack bot for posting dank memes from Reddit
Home-page: https://github.com/DankCity/dankbot
Author: Levi Noecker
Author-email: levi [at] dank [dot] city
License: MIT
Keywords: reddit,slack,imgur,dank,memes,bot,slack bot,dankbot
Platform: UNKNOWN
Classifier: Development Status :: 3 - Alpha
Classifier: Intended Audience :: Developers
Classifier: Natural Language :: English
Classifier: License :: OSI Approved :: MIT License
Classifier: Operating System :: OS Independent
Classifier: Topic :: Communications :: Chat
Classifier: Programming Language :: Python :: 2
Classifier: Programming Language :: Python :: 2.7
Classifier: Programming Language :: Python :: 3
Classifier: Programming Language :: Python :: 3.4
Classifier: Programming Language :: Python :: 3.5
Classifier: Programming Language :: Python :: 3.6
Classifier: Programming Language :: Python :: Implementation :: CPython
Classifier: Programming Language :: Python :: Implementation :: PyPy
Requires-Dist: appdirs (==1.4.0)
Requires-Dist: configparser (==3.5.0)
Requires-Dist: imgurpython (==1.1.7)
Requires-Dist: praw (==3.6.0)
Requires-Dist: retryz (==0.1.8)
Requires-Dist: slacker (==0.9.30)
